jellyfaas_calebmhartshorn/__init__.py
jellyfaas_calebmhartshorn/jellyfaas.py
jellyfaas_calebmhartshorn-0.0.2.dist-info/METADATA
jellyfaas_calebmhartshorn-0.0.2.dist-info/WHEEL
jellyfaas_calebmhartshorn-0.0.2.dist-info/licenses/LICENSE
jellyfaas_calebmhartshorn-0.0.2.dist-info/RECORD
