Metadata-Version: 2.3
Name: jellyfaas_calebmhartshorn
Version: 0.0.2
Summary: A client for interacting with the JellyFAAS API
Author-email: Caleb Hartshorn <caleb@platform48.com>
License: TEST
License-File: LICENSE
Requires-Dist: requests
